docs/conf.py
examples/examples.py
googlesat/__init__.py
googlesat/downloader.py
googlesat/sentinel.py
googlesat/utils.py
googlesat/aux/sentinel-2_tiling_grid.geojson
tests/test_geometry_from_file.py
tests/test_get_metadata.py
tests/test_query.py
googlesat-0.0.1a1.dist-info/LICENSE
googlesat-0.0.1a1.dist-info/METADATA
googlesat-0.0.1a1.dist-info/WHEEL
googlesat-0.0.1a1.dist-info/top_level.txt
googlesat-0.0.1a1.dist-info/RECORD
