Metadata-Version: 2.1
Name: googlesat
Version: 0.0.1a1
Summary: Download Sentinel 2 data from GCP
Home-page: https://googlesat.readthedocs.io/en/latest/
Author: Falagas Alekos
Author-email: Alekos Falagas <alek.falagas@gmail.com>
Maintainer-email: Alekos Falagas <alek.falagas@gmail.com>
License: MIT
Classifier: Intended Audience :: Science/Research
Classifier: Operating System :: OS Independent
Classifier: Programming Language :: Python :: 3.9
Classifier: Programming Language :: Python :: 3.10
Classifier: Programming Language :: Python :: 3.11
Classifier: Topic :: Scientific/Engineering :: GIS
Requires-Python: >=3.9
License-File: LICENSE
Requires-Dist: platformdirs
Requires-Dist: pandas
Requires-Dist: geopandas
Requires-Dist: rtree
Provides-Extra: dev
Requires-Dist: pytest ; extra == 'dev'
Requires-Dist: pytest-cov ; extra == 'dev'
Requires-Dist: pytest-dependency ; extra == 'dev'
Requires-Dist: pytest-lazy-fixture ; extra == 'dev'
Requires-Dist: pytest-mock ; extra == 'dev'
Provides-Extra: docs
Requires-Dist: sphinx ; extra == 'docs'
Requires-Dist: sphinxcontrib-apidoc ; extra == 'docs'
Requires-Dist: sphinxcontrib-napoleon ; extra == 'docs'
Requires-Dist: sphinx-rtd-theme ; extra == 'docs'
Requires-Dist: myst-parser ; extra == 'docs'
Requires-Dist: sphinxemoji ; extra == 'docs'
